{
  "table_name": "blocks",
  "total_rows": 2000,
  "sampled": false,
  "analyzed_rows": 2000,
  "columns": {},
  "column_summary": {
    "hash": {
      "dtype": "String",
      "null_count": 0,
      "null_pct": 0.0,
      "distinct_count": 2000,
      "status": "OK"
    },
    "size": {
      "dtype": "Int64",
      "null_count": 0,
      "null_pct": 0.0,
      "distinct_count": 132,
      "status": "NOT_CHECKED"
    },
    "stripped_size": {
      "dtype": "Int64",
      "null_count": 0,
      "null_pct": 0.0,
      "distinct_count": 132,
      "status": "NOT_CHECKED"
    },
    "weight": {
      "dtype": "Int64",
      "null_count": 0,
      "null_pct": 0.0,
      "distinct_count": 132,
      "status": "NOT_CHECKED"
    },
    "number": {
      "dtype": "Int64",
      "null_count": 0,
      "null_pct": 0.0,
      "distinct_count": 2000,
      "status": "NOT_CHECKED"
    },
    "version": {
      "dtype": "Int64",
      "null_count": 0,
      "null_pct": 0.0,
      "distinct_count": 24,
      "status": "NOT_CHECKED"
    },
    "merkle_root": {
      "dtype": "String",
      "null_count": 0,
      "null_pct": 0.0,
      "distinct_count": 2000,
      "status": "OK"
    },
    "timestamp": {
      "dtype": "Datetime(time_unit='ns', time_zone='UTC')",
      "null_count": 0,
      "null_pct": 0.0,
      "distinct_count": 1999,
      "status": "OK"
    },
    "timestamp_month": {
      "dtype": "Date",
      "null_count": 0,
      "null_pct": 0.0,
      "distinct_count": 2,
      "status": "OK"
    },
    "nonce": {
      "dtype": "String",
      "null_count": 0,
      "null_pct": 0.0,
      "distinct_count": 2000,
      "status": "OK"
    },
    "bits": {
      "dtype": "String",
      "null_count": 0,
      "null_pct": 0.0,
      "distinct_count": 4,
      "status": "OK"
    },
    "coinbase_param": {
      "dtype": "String",
      "null_count": 0,
      "null_pct": 0.0,
      "distinct_count": 729,
      "status": "OK"
    },
    "transaction_count": {
      "dtype": "Int64",
      "null_count": 0,
      "null_pct": 0.0,
      "distinct_count": 27,
      "status": "NOT_CHECKED"
    }
  },
  "column_insights": {
    "hash": {
      "top_values": [
        {
          "value": "000000003649bfe1bd1cc0f8a5ec1e063663924d2d09196c5874e09ab73a4df3",
          "count": 1,
          "percentage": 0.05
        },
        {
          "value": "000000002da3382ca3e6454def19a42c2b815891020a1cfb30430427ecb9c735",
          "count": 1,
          "percentage": 0.05
        },
        {
          "value": "000000002f43c3af499c50d8c92d1ad662331adf3a44467bd3351445c9e2fae9",
          "count": 1,
          "percentage": 0.05
        },
        {
          "value": "000000002983fc5d1e550a8712418e5e00c21a6dd34c0f21dae8d3f9b86ca737",
          "count": 1,
          "percentage": 0.05
        },
        {
          "value": "000000002777549261e114d8241db1c79d8e4e551e21b266a0af017ad9a61227",
          "count": 1,
          "percentage": 0.05
        },
        {
          "value": "00000000094aaed946078c8e9ef035234180aaf6172e203ab7fabcd0e661c0a7",
          "count": 1,
          "percentage": 0.05
        },
        {
          "value": "000000001bac24925f27fcda68f03651bf850f16fe818987e91181e7753f9523",
          "count": 1,
          "percentage": 0.05
        },
        {
          "value": "0000000025bf189a0b8cc87eb21de18e8cbe741b886eac1939f4b17655a26556",
          "count": 1,
          "percentage": 0.05
        },
        {
          "value": "0000000030e2eea516ddc719c88cb095ae7489ca1a4eb61538610a4cc5cade60",
          "count": 1,
          "percentage": 0.05
        },
        {
          "value": "00000000098babbafaae7a23f42510841d48ef228675c669b2c1faf5f4a60765",
          "count": 1,
          "percentage": 0.05
        }
      ],
      "length_stats": {
        "min": 64,
        "max": 64,
        "avg": 64.0
      }
    },
    "size": {
      "min": 215.0,
      "max": 2032370.0,
      "mean": 15856.4655,
      "median": 215.0,
      "quantiles": {
        "p25": 215.0,
        "p50": 215.0,
        "p75": 215.0
      },
      "top_values": [
        {
          "value": 215.0,
          "count": 1511,
          "percentage": 75.55
        },
        {
          "value": 216.0,
          "count": 304,
          "percentage": 15.2
        },
        {
          "value": 374.0,
          "count": 19,
          "percentage": 0.95
        },
        {
          "value": 449.0,
          "count": 5,
          "percentage": 0.25
        },
        {
          "value": 487.0,
          "count": 4,
          "percentage": 0.2
        }
      ]
    },
    "stripped_size": {
      "min": 215.0,
      "max": 813529.0,
      "mean": 7329.8485,
      "median": 215.0,
      "quantiles": {
        "p25": 215.0,
        "p50": 215.0,
        "p75": 215.0
      },
      "top_values": [
        {
          "value": 215.0,
          "count": 1511,
          "percentage": 75.55
        },
        {
          "value": 216.0,
          "count": 304,
          "percentage": 15.2
        },
        {
          "value": 374.0,
          "count": 19,
          "percentage": 0.95
        },
        {
          "value": 449.0,
          "count": 5,
          "percentage": 0.25
        },
        {
          "value": 488.0,
          "count": 4,
          "percentage": 0.2
        }
      ]
    },
    "weight": {
      "min": 860.0,
      "max": 3994104.0,
      "mean": 37846.011,
      "median": 860.0,
      "quantiles": {
        "p25": 860.0,
        "p50": 860.0,
        "p75": 860.0
      },
      "top_values": [
        {
          "value": 860.0,
          "count": 1511,
          "percentage": 75.55
        },
        {
          "value": 864.0,
          "count": 304,
          "percentage": 15.2
        },
        {
          "value": 1496.0,
          "count": 19,
          "percentage": 0.95
        },
        {
          "value": 1796.0,
          "count": 5,
          "percentage": 0.25
        },
        {
          "value": 1948.0,
          "count": 4,
          "percentage": 0.2
        }
      ]
    },
    "number": {
      "min": 43097.0,
      "max": 920112.0,
      "mean": 55951.0445,
      "median": 45988.0,
      "quantiles": {
        "p25": 44743.0,
        "p50": 45989.0,
        "p75": 47155.0
      },
      "top_values": [
        {
          "value": 44091.0,
          "count": 1,
          "percentage": 0.05
        },
        {
          "value": 47729.0,
          "count": 1,
          "percentage": 0.05
        },
        {
          "value": 43820.0,
          "count": 1,
          "percentage": 0.05
        },
        {
          "value": 46547.0,
          "count": 1,
          "percentage": 0.05
        },
        {
          "value": 46273.0,
          "count": 1,
          "percentage": 0.05
        }
      ]
    },
    "version": {
      "min": 1.0,
      "max": 1015758848.0,
      "mean": 7227634.6525,
      "median": 1.0,
      "quantiles": {
        "p25": 1.0,
        "p50": 1.0,
        "p75": 1.0
      },
      "top_values": [
        {
          "value": 1.0,
          "count": 1977,
          "percentage": 98.85000000000001
        },
        {
          "value": 606371840.0,
          "count": 1,
          "percentage": 0.05
        },
        {
          "value": 537575424.0,
          "count": 1,
          "percentage": 0.05
        },
        {
          "value": 572325888.0,
          "count": 1,
          "percentage": 0.05
        },
        {
          "value": 537698304.0,
          "count": 1,
          "percentage": 0.05
        }
      ]
    },
    "merkle_root": {
      "top_values": [
        {
          "value": "c6425b8e359b8392838b19e7049ef4c14f4a7fd8ac1a399377448dfb751c45ff",
          "count": 1,
          "percentage": 0.05
        },
        {
          "value": "6216d24ef40415d50ed3886ab0392b927454a46d6a21ad476d9227e2035610a5",
          "count": 1,
          "percentage": 0.05
        },
        {
          "value": "b4e811a4de13967b02f07710c3bdc9a52a2611aef14e523a791b94ce5ca78eda",
          "count": 1,
          "percentage": 0.05
        },
        {
          "value": "1f995dbd98897238a9667c6f9ce4413f1db1d447112ebdbf8d71f3f2444a45ea",
          "count": 1,
          "percentage": 0.05
        },
        {
          "value": "68f7653a1acebfdeb24ea94a8f42b9ecd9e42e5996e7c25a922718f8a7236c68",
          "count": 1,
          "percentage": 0.05
        },
        {
          "value": "848b0a9c89815b2f321166998e5a02349de91798fca5f9eca2e5a27024d2c178",
          "count": 1,
          "percentage": 0.05
        },
        {
          "value": "e28dac80b391704acba22c8399eb4af229861be87cf0fe2e81296a9cac956be2",
          "count": 1,
          "percentage": 0.05
        },
        {
          "value": "25f43d1c395c43d9202f1d9468e01d37cd95b7ac459ae454c93041ceeffb7699",
          "count": 1,
          "percentage": 0.05
        },
        {
          "value": "9bdb09c5cf160e8dcc4b1bff0f4ab9b902eb95c4795f789c18ccbe64db8e889f",
          "count": 1,
          "percentage": 0.05
        },
        {
          "value": "3806278df554df842c144a9209783a0f9798b89bfcd914ac256d2f6c601b0089",
          "count": 1,
          "percentage": 0.05
        }
      ],
      "length_stats": {
        "min": 64,
        "max": 64,
        "avg": 64.0
      }
    },
    "timestamp": {
      "min_date": "2010-03-01 00:06:51+00:00",
      "max_date": "2025-10-21 13:04:48+00:00",
      "date_range_days": 5713,
      "most_common_dates": [
        {
          "date": "2010-03-23",
          "count": 103,
          "percentage": 5.1499999999999995
        },
        {
          "date": "2010-03-25",
          "count": 98,
          "percentage": 4.9
        },
        {
          "date": "2010-03-30",
          "count": 96,
          "percentage": 4.8
        },
        {
          "date": "2010-03-29",
          "count": 95,
          "percentage": 4.75
        },
        {
          "date": "2010-03-26",
          "count": 89,
          "percentage": 4.45
        }
      ],
      "most_common_hours": [
        {
          "hour": 23,
          "count": 122,
          "percentage": 6.1
        },
        {
          "hour": 21,
          "count": 105,
          "percentage": 5.25
        },
        {
          "hour": 18,
          "count": 103,
          "percentage": 5.1499999999999995
        },
        {
          "hour": 2,
          "count": 100,
          "percentage": 5.0
        },
        {
          "hour": 22,
          "count": 90,
          "percentage": 4.5
        },
        {
          "hour": 4,
          "count": 89,
          "percentage": 4.45
        },
        {
          "hour": 16,
          "count": 89,
          "percentage": 4.45
        },
        {
          "hour": 9,
          "count": 88,
          "percentage": 4.3999999999999995
        },
        {
          "hour": 0,
          "count": 87,
          "percentage": 4.35
        },
        {
          "hour": 7,
          "count": 84,
          "percentage": 4.2
        }
      ],
      "most_common_days": [
        {
          "day": "Tuesday",
          "weekday": 2,
          "count": 372,
          "percentage": 18.6
        },
        {
          "day": "Monday",
          "weekday": 1,
          "count": 332,
          "percentage": 16.6
        },
        {
          "day": "Wednesday",
          "weekday": 3,
          "count": 309,
          "percentage": 15.45
        },
        {
          "day": "Thursday",
          "weekday": 4,
          "count": 265,
          "percentage": 13.25
        },
        {
          "day": "Friday",
          "weekday": 5,
          "count": 264,
          "percentage": 13.200000000000001
        },
        {
          "day": "Saturday",
          "weekday": 6,
          "count": 234,
          "percentage": 11.700000000000001
        },
        {
          "day": "Sunday",
          "weekday": 7,
          "count": 224,
          "percentage": 11.200000000000001
        }
      ],
      "timezone": "UTC"
    },
    "timestamp_month": {
      "min_date": "2010-03-01",
      "max_date": "2025-10-01",
      "date_range_days": 5693,
      "most_common_dates": [
        {
          "date": "2010-03-01",
          "count": 1977,
          "percentage": 98.85000000000001
        },
        {
          "date": "2025-10-01",
          "count": 23,
          "percentage": 1.15
        }
      ],
      "most_common_days": [
        {
          "day": "Monday",
          "weekday": 1,
          "count": 1977,
          "percentage": 98.85000000000001
        },
        {
          "day": "Wednesday",
          "weekday": 3,
          "count": 23,
          "percentage": 1.15
        }
      ],
      "timezone": "None (timezone-naive)"
    },
    "nonce": {
      "top_values": [
        {
          "value": "30b01c3",
          "count": 1,
          "percentage": 0.05
        },
        {
          "value": "f1d3cc",
          "count": 1,
          "percentage": 0.05
        },
        {
          "value": "12c25e65",
          "count": 1,
          "percentage": 0.05
        },
        {
          "value": "494d81c",
          "count": 1,
          "percentage": 0.05
        },
        {
          "value": "d350b1",
          "count": 1,
          "percentage": 0.05
        },
        {
          "value": "153a482",
          "count": 1,
          "percentage": 0.05
        },
        {
          "value": "8daf253",
          "count": 1,
          "percentage": 0.05
        },
        {
          "value": "5868101",
          "count": 1,
          "percentage": 0.05
        },
        {
          "value": "6eb1cf06",
          "count": 1,
          "percentage": 0.05
        },
        {
          "value": "ee8345",
          "count": 1,
          "percentage": 0.05
        }
      ],
      "length_stats": {
        "min": 3,
        "max": 8,
        "avg": 7.13
      }
    },
    "bits": {
      "top_values": [
        {
          "value": "1c381375",
          "count": 860,
          "percentage": 43.0
        },
        {
          "value": "1c387f6f",
          "count": 754,
          "percentage": 37.7
        },
        {
          "value": "1c43b3e5",
          "count": 363,
          "percentage": 18.15
        },
        {
          "value": "1701eb21",
          "count": 23,
          "percentage": 1.15
        }
      ],
      "length_stats": {
        "min": 8,
        "max": 8,
        "avg": 8.0
      }
    },
    "coinbase_param": {
      "top_values": [
        {
          "value": "047513381c0102",
          "count": 17,
          "percentage": 0.8500000000000001
        },
        {
          "value": "046f7f381c0102",
          "count": 16,
          "percentage": 0.8
        },
        {
          "value": "046f7f381c0107",
          "count": 16,
          "percentage": 0.8
        },
        {
          "value": "046f7f381c0103",
          "count": 15,
          "percentage": 0.75
        },
        {
          "value": "046f7f381c010b",
          "count": 15,
          "percentage": 0.75
        },
        {
          "value": "046f7f381c0109",
          "count": 14,
          "percentage": 0.7000000000000001
        },
        {
          "value": "046f7f381c0108",
          "count": 12,
          "percentage": 0.6
        },
        {
          "value": "047513381c0109",
          "count": 11,
          "percentage": 0.5499999999999999
        },
        {
          "value": "047513381c0103",
          "count": 11,
          "percentage": 0.5499999999999999
        },
        {
          "value": "046f7f381c0113",
          "count": 10,
          "percentage": 0.5
        }
      ],
      "length_stats": {
        "min": 14,
        "max": 200,
        "avg": 16.25
      }
    },
    "transaction_count": {
      "min": 1.0,
      "max": 5633.0,
      "mean": 36.398,
      "median": 1.0,
      "quantiles": {
        "p25": 1.0,
        "p50": 1.0,
        "p75": 1.0
      },
      "top_values": [
        {
          "value": 1.0,
          "count": 1816,
          "percentage": 90.8
        },
        {
          "value": 2.0,
          "count": 134,
          "percentage": 6.7
        },
        {
          "value": 3.0,
          "count": 22,
          "percentage": 1.0999999999999999
        },
        {
          "value": 4.0,
          "count": 5,
          "percentage": 0.25
        },
        {
          "value": 3319.0,
          "count": 1,
          "percentage": 0.05
        }
      ]
    }
  },
  "timestamp": "2025-10-21T15:52:30.888454",
  "start_time": "2025-10-21T15:52:30.888454",
  "check_durations": {
    "string_checks": 0.023135999999999997,
    "date_checks": 0.007845999999999999
  },
  "potential_primary_keys": [
    "hash",
    "number",
    "merkle_root",
    "nonce"
  ],
  "end_time": "2025-10-21T15:52:30.933763",
  "duration_seconds": 0.05,
  "table_metadata": {
    "table_name": "blocks",
    "table_type": "BASE TABLE",
    "created_time": "2019-01-14 18:28:17.012000+00:00",
    "table_uid": "bigquery-public-data.crypto_bitcoin.blocks",
    "row_count": 2000,
    "primary_key_columns": [
      "block_id"
    ],
    "primary_key_source": "user_config",
    "query_result_count": 2000
  },
  "phase_timings": {
    "connection": 0.413772,
    "metadata": 7.120104,
    "data_loading": 3.442727,
    "audit_checks": 0.047043
  }
}